furry_art_sync/__init__.py
furry_art_sync/datastore.py
furry_art_sync/sites/__init__.py
furry_art_sync/sites/post.py
furry_art_sync/sites/post_match.py
furry_art_sync/sites/site.py
furry_art_sync/sites/site_furaffinity.py
furry_art_sync/sites/site_weasyl.py
furry_art_sync/tool.py
furry_art_sync-0.1.0.dist-info/LICENSE
furry_art_sync-0.1.0.dist-info/METADATA
furry_art_sync-0.1.0.dist-info/WHEEL
furry_art_sync-0.1.0.dist-info/RECORD
